pyacaia_async/__init__.py
pyacaia_async/acaiascale.py
pyacaia_async/const.py
pyacaia_async/decode.py
pyacaia_async/exceptions.py
pyacaia_async/helpers.py
pyacaia_async/py.typed
pyacaia_async-0.1.2.dist-info/LICENSE
pyacaia_async-0.1.2.dist-info/METADATA
pyacaia_async-0.1.2.dist-info/WHEEL
pyacaia_async-0.1.2.dist-info/top_level.txt
pyacaia_async-0.1.2.dist-info/RECORD
